aynse/__init__.py
aynse/cli.py
aynse/holidays.py
aynse/py.typed
aynse/util.py
aynse/nse/__init__.py
aynse/nse/archives.py
aynse/nse/connection_pool.py
aynse/nse/history.py
aynse/nse/http_client.py
aynse/nse/live.py
aynse/nse/request_batcher.py
aynse/nse/streaming_processor.py
aynse/rbi/__init__.py
aynse/rbi/historical.py
aynse-1.3.0.dist-info/licenses/LICENSE.md
aynse-1.3.0.dist-info/METADATA
aynse-1.3.0.dist-info/WHEEL
aynse-1.3.0.dist-info/entry_points.txt
aynse-1.3.0.dist-info/top_level.txt
aynse-1.3.0.dist-info/RECORD
