Metadata-Version: 2.4
Name: aynse
Version: 1.3.0
Summary: A lean and modern Python library to fetch data from NSE (National Stock Exchange of India)
Author-email: satyam-kashyap <satyamsudo@gmail.com>
License-Expression: MIT
Project-URL: Homepage, https://satyamkashyap.com/aynse
Project-URL: Documentation, https://satyamkashyap.com/aynse
Project-URL: Repository, https://github.com/sudotman/aynse
Project-URL: Issues, https://github.com/sudotman/aynse/issues
Project-URL: Changelog, https://github.com/sudotman/aynse/releases
Keywords: nse,bhavcopy,aynse,stock,market,india,finance
Classifier: Development Status :: 4 - Beta
Classifier: Programming Language :: Python :: 3
Classifier: Programming Language :: Python :: 3.9
Classifier: Programming Language :: Python :: 3.10
Classifier: Programming Language :: Python :: 3.11
Classifier: Programming Language :: Python :: 3.12
Classifier: Operating System :: OS Independent
Classifier: Intended Audience :: Developers
Classifier: Intended Audience :: Financial and Insurance Industry
Classifier: Topic :: Office/Business :: Financial :: Investment
Classifier: Topic :: Software Development :: Libraries :: Python Modules
Classifier: Typing :: Typed
Requires-Python: >=3.9
License-File: LICENSE.md
Provides-Extra: dev
Requires-Dist: pytest>=7.4.0; extra == "dev"
Requires-Dist: pytest-cov>=4.1.0; extra == "dev"
Requires-Dist: pytest-asyncio>=0.21.0; extra == "dev"
Requires-Dist: pyfakefs; extra == "dev"
Requires-Dist: mypy>=1.0.0; extra == "dev"
Requires-Dist: types-requests>=2.31.0; extra == "dev"
Provides-Extra: docs
Requires-Dist: mkdocs>=1.6.0; extra == "docs"
Requires-Dist: mkdocs-material>=9.5.0; extra == "docs"
Requires-Dist: mkdocstrings[python]>=0.25.0; extra == "docs"
Dynamic: license-file
